{
  "user_id": "8d70855e-1c79-4912-ad1e-eacfee297cd2",
  "title": "Customer Feedback Survey",
  "visibility": true,
  "question_type": "Multiple Type",
  "created_at": "2024-03-09 11:32:53",
  "description": "Thank you for being a valued customer! Your input is essential to help us improve our products and services. This survey will take only a few minutes.",
  "expiry_date": "2025-01-24",
  "randomize": true,
  "id": "3eada031-35a4-4569-9c98-0525d43de043",
  "updated_at": "2024-03-09 11:32:53",
  "__class__": "Survey",
  "questions": [
    {
      "random": true,
      "survey_id": "3eada031-35a4-4569-9c98-0525d43de043",
      "created_at": "2024-03-09 11:32:56",
      "options": [
        "Extremely likely",
        "Likely",
        "Neutral",
        "Unlikely",
        "Extremely unlikely"
      ],
      "question": "How likely are you to purchase from us again?",
      "id": "01f702fc-5ae6-4850-b7aa-d53b4b061f90",
      "updated_at": "2024-03-09 11:32:56",
      "__class__": "Question"
    },
    {
      "random": true,
      "survey_id": "3eada031-35a4-4569-9c98-0525d43de043",
      "created_at": "2024-03-09 11:32:55",
      "options": [
        "Extremely satisfied",
        "Satisfied",
        "Neutral",
        "Dissatisfied",
        "Extremely dissatisfied"
      ],
      "question": "What is your overall satisfaction with our products/services?",
      "id": "26eeecd9-1d5f-4736-8c02-8163ab47d4a4",
      "updated_at": "2024-03-09 11:32:55",
      "__class__": "Question"
    },
    {
      "random": true,
      "survey_id": "3eada031-35a4-4569-9c98-0525d43de043",
      "created_at": "2024-03-09 11:32:55",
      "options": [
        "Excellent",
        "Very good",
        "Good",
        "Fair",
        "Poor"
      ],
      "question": "How would you rate the quality of our products/services?",
      "id": "2c3453b8-f07b-449c-9082-645aaf20110b",
      "updated_at": "2024-03-09 11:32:55",
      "__class__": "Question"
    },
    {
      "random": true,
      "survey_id": "3eada031-35a4-4569-9c98-0525d43de043",
      "created_at": "2024-03-09 11:32:56",
      "options": [
        "Excellent",
        "Very good",
        "Good",
        "Fair",
        "Poor"
      ],
      "question": "How would you rate our customer service?",
      "id": "7608d6a2-3f1e-4916-8932-12965909b3c1",
      "updated_at": "2024-03-09 11:32:56",
      "__class__": "Question"
    },
    {
      "random": true,
      "survey_id": "3eada031-35a4-4569-9c98-0525d43de043",
      "created_at": "2024-03-09 11:32:55",
      "options": [
        "Friend/Family referral",
        "Online search",
        "Social media",
        "Advertisement",
        "Other (please specify)"
      ],
      "question": "How did you hear about our company?",
      "id": "9b990472-85f5-4622-b340-4944b160020e",
      "updated_at": "2024-03-09 11:32:55",
      "__class__": "Question"
    },
    {
      "random": true,
      "survey_id": "3eada031-35a4-4569-9c98-0525d43de043",
      "created_at": "2024-03-09 11:32:56",
      "options": [
        "Definitely yes",
        "Probably yes",
        "Might or might not",
        "Probably not",
        "Definitely not"
      ],
      "question": "Would you recommend our company to a friend or colleague?",
      "id": "aaf68f76-f975-48df-8760-dc333aef5ac6",
      "updated_at": "2024-03-09 11:32:56",
      "__class__": "Question"
    },
    {
      "random": true,
      "survey_id": "3eada031-35a4-4569-9c98-0525d43de043",
      "created_at": "2024-03-09 11:32:54",
      "options": [
        "Daily",
        "Weekly",
        "Monthly",
        "Occasionally",
        "First-time customer"
      ],
      "question": "How often do you purchase our products?",
      "id": "dc9b9442-3703-40f8-b715-a873fdd619f3",
      "updated_at": "2024-03-09 11:32:54",
      "__class__": "Question"
    },
    {
      "random": true,
      "survey_id": "3eada031-35a4-4569-9c98-0525d43de043",
      "created_at": "2024-03-09 11:32:56",
      "options": [
        "Very easy",
        "Easy",
        "Neutral",
        "Difficult",
        "Very difficult"
      ],
      "question": "How easy is it to find the products/services you need on our website/in our store?",
      "id": "ed93db8c-29a0-453e-bef9-f5e0faf85a8e",
      "updated_at": "2024-03-09 11:32:56",
      "__class__": "Question"
    },
    {
      "random": true,
      "survey_id": "3eada031-35a4-4569-9c98-0525d43de043",
      "created_at": "2024-03-09 11:32:57",
      "options": [
        "18-25",
        "26-35",
        "36-45",
        "46-55",
        "56+"
      ],
      "question": "What is your age range?",
      "id": "efce93d3-e2fb-4f5f-b05c-f26c19cfd126",
      "updated_at": "2024-03-09 11:32:57",
      "__class__": "Question"
    }
  ],
  "responses": [
    {
      "bio": {
        "name": "Okeomasilachi",
        "sex": "trans-Gender"
      },
      "timestamp": "2024-03-09 11:08:15",
      "id": "0c708686-3e06-411d-86fa-559d2035ef8e",
      "updated_at": "2024-03-09 11:37:52",
      "survey_id": "3eada031-35a4-4569-9c98-0525d43de043",
      "answers": [
        {
          "question_id": "01f702fc-5ae6-4850-b7aa-d53b4b061f90",
          "response": [
            "Extremely likely"
          ]
        },
        {
          "question_id": "26eeecd9-1d5f-4736-8c02-8163ab47d4a4",
          "response": [
            "Satisfied"
          ]
        },
        {
          "question_id": "2c3453b8-f07b-449c-9082-645aaf20110b",
          "response": [
            "Very good"
          ]
        },
        {
          "question_id": "7608d6a2-3f1e-4916-8932-12965909b3c1",
          "response": [
            "Very good"
          ]
        },
        {
          "question_id": "9b990472-85f5-4622-b340-4944b160020e",
          "response": [
            "Social media"
          ]
        },
        {
          "question_id": "aaf68f76-f975-48df-8760-dc333aef5ac6",
          "response": [
            "Probably not"
          ]
        },
        {
          "question_id": "dc9b9442-3703-40f8-b715-a873fdd619f3",
          "response": [
            "First-time customer"
          ]
        },
        {
          "question_id": "ed93db8c-29a0-453e-bef9-f5e0faf85a8e",
          "response": [
            "Very difficult"
          ]
        },
        {
          "question_id": "efce93d3-e2fb-4f5f-b05c-f26c19cfd126",
          "response": [
            "26-35"
          ]
        }
      ],
      "created_at": "2024-03-09 11:37:52",
      "__class__": "Response"
    },
    {
      "bio": {
        "name": "Okeomasilachi",
        "sex": "female"
      },
      "timestamp": "2024-03-09 12:38:57",
      "id": "22654c24-9289-447c-a7c2-969b5bf61a62",
      "updated_at": "2024-03-09 12:44:16",
      "survey_id": "3eada031-35a4-4569-9c98-0525d43de043",
      "answers": [
        {
          "question_id": "01f702fc-5ae6-4850-b7aa-d53b4b061f90",
          "response": [
            "Extremely likely"
          ]
        },
        {
          "question_id": "26eeecd9-1d5f-4736-8c02-8163ab47d4a4",
          "response": [
            "Extremely dissatisfied"
          ]
        },
        {
          "question_id": "2c3453b8-f07b-449c-9082-645aaf20110b",
          "response": [
            "Very good"
          ]
        },
        {
          "question_id": "7608d6a2-3f1e-4916-8932-12965909b3c1",
          "response": [
            "Poor"
          ]
        },
        {
          "question_id": "9b990472-85f5-4622-b340-4944b160020e",
          "response": [
            "Other (please specify)"
          ]
        },
        {
          "question_id": "aaf68f76-f975-48df-8760-dc333aef5ac6",
          "response": [
            "Probably not"
          ]
        },
        {
          "question_id": "dc9b9442-3703-40f8-b715-a873fdd619f3",
          "response": [
            "Occasionally"
          ]
        },
        {
          "question_id": "ed93db8c-29a0-453e-bef9-f5e0faf85a8e",
          "response": [
            "Very easy"
          ]
        },
        {
          "question_id": "efce93d3-e2fb-4f5f-b05c-f26c19cfd126",
          "response": [
            "18-25"
          ]
        }
      ],
      "created_at": "2024-03-09 12:44:16",
      "__class__": "Response"
    },
    {
      "bio": {
        "name": "Okeomasilachi",
        "sex": "female"
      },
      "timestamp": "2024-03-09 12:38:57",
      "id": "23a5787b-de9b-4233-b14b-203429d2d6fb",
      "updated_at": "2024-03-09 12:44:16",
      "survey_id": "3eada031-35a4-4569-9c98-0525d43de043",
      "answers": [
        {
          "question_id": "01f702fc-5ae6-4850-b7aa-d53b4b061f90",
          "response": [
            "Extremely likely"
          ]
        },
        {
          "question_id": "26eeecd9-1d5f-4736-8c02-8163ab47d4a4",
          "response": [
            "Extremely dissatisfied"
          ]
        },
        {
          "question_id": "2c3453b8-f07b-449c-9082-645aaf20110b",
          "response": [
            "Very good"
          ]
        },
        {
          "question_id": "7608d6a2-3f1e-4916-8932-12965909b3c1",
          "response": [
            "Poor"
          ]
        },
        {
          "question_id": "9b990472-85f5-4622-b340-4944b160020e",
          "response": [
            "Other (please specify)"
          ]
        },
        {
          "question_id": "aaf68f76-f975-48df-8760-dc333aef5ac6",
          "response": [
            "Probably not"
          ]
        },
        {
          "question_id": "dc9b9442-3703-40f8-b715-a873fdd619f3",
          "response": [
            "Occasionally"
          ]
        },
        {
          "question_id": "ed93db8c-29a0-453e-bef9-f5e0faf85a8e",
          "response": [
            "Very easy"
          ]
        },
        {
          "question_id": "efce93d3-e2fb-4f5f-b05c-f26c19cfd126",
          "response": [
            "18-25"
          ]
        }
      ],
      "created_at": "2024-03-09 12:44:16",
      "__class__": "Response"
    },
    {
      "bio": {
        "name": "Okeomasilachi",
        "sex": "male"
      },
      "timestamp": "2024-03-09 12:03:29",
      "id": "354dfcd5-797f-436c-ab38-9f8b0b0bb182",
      "updated_at": "2024-03-09 12:20:28",
      "survey_id": "3eada031-35a4-4569-9c98-0525d43de043",
      "answers": [
        {
          "question_id": "01f702fc-5ae6-4850-b7aa-d53b4b061f90",
          "response": [
            "Extremely likely"
          ]
        },
        {
          "question_id": "26eeecd9-1d5f-4736-8c02-8163ab47d4a4",
          "response": [
            "Extremely satisfied"
          ]
        },
        {
          "question_id": "2c3453b8-f07b-449c-9082-645aaf20110b",
          "response": [
            "Excellent"
          ]
        },
        {
          "question_id": "7608d6a2-3f1e-4916-8932-12965909b3c1",
          "response": [
            "Good"
          ]
        },
        {
          "question_id": "9b990472-85f5-4622-b340-4944b160020e",
          "response": [
            "Online search"
          ]
        },
        {
          "question_id": "aaf68f76-f975-48df-8760-dc333aef5ac6",
          "response": [
            "Probably yes"
          ]
        },
        {
          "question_id": "dc9b9442-3703-40f8-b715-a873fdd619f3",
          "response": [
            "Occasionally"
          ]
        },
        {
          "question_id": "ed93db8c-29a0-453e-bef9-f5e0faf85a8e",
          "response": [
            "Very difficult"
          ]
        },
        {
          "question_id": "efce93d3-e2fb-4f5f-b05c-f26c19cfd126",
          "response": [
            "36-45"
          ]
        }
      ],
      "created_at": "2024-03-09 12:20:28",
      "__class__": "Response"
    },
    {
      "bio": {
        "name": "Henry",
        "sex": "male"
      },
      "timestamp": "2024-03-09 12:38:57",
      "id": "4030a6fd-602e-4249-9b77-27f1900f97ce",
      "updated_at": "2024-03-09 12:49:35",
      "survey_id": "3eada031-35a4-4569-9c98-0525d43de043",
      "answers": [
        {
          "question_id": "01f702fc-5ae6-4850-b7aa-d53b4b061f90",
          "response": []
        },
        {
          "question_id": "26eeecd9-1d5f-4736-8c02-8163ab47d4a4",
          "response": []
        },
        {
          "question_id": "2c3453b8-f07b-449c-9082-645aaf20110b",
          "response": []
        },
        {
          "question_id": "7608d6a2-3f1e-4916-8932-12965909b3c1",
          "response": []
        },
        {
          "question_id": "9b990472-85f5-4622-b340-4944b160020e",
          "response": []
        },
        {
          "question_id": "aaf68f76-f975-48df-8760-dc333aef5ac6",
          "response": []
        },
        {
          "question_id": "dc9b9442-3703-40f8-b715-a873fdd619f3",
          "response": []
        },
        {
          "question_id": "ed93db8c-29a0-453e-bef9-f5e0faf85a8e",
          "response": []
        },
        {
          "question_id": "efce93d3-e2fb-4f5f-b05c-f26c19cfd126",
          "response": []
        }
      ],
      "created_at": "2024-03-09 12:49:35",
      "__class__": "Response"
    },
    {
      "bio": {
        "name": "Henry",
        "sex": "female"
      },
      "timestamp": "2024-03-09 12:38:57",
      "id": "4c6bc092-6cbe-4656-bfa9-c9c869f5be48",
      "updated_at": "2024-03-09 12:45:49",
      "survey_id": "3eada031-35a4-4569-9c98-0525d43de043",
      "answers": [
        {
          "question_id": "01f702fc-5ae6-4850-b7aa-d53b4b061f90",
          "response": [
            "Extremely likely",
            "Extremely unlikely"
          ]
        },
        {
          "question_id": "26eeecd9-1d5f-4736-8c02-8163ab47d4a4",
          "response": [
            "Dissatisfied"
          ]
        },
        {
          "question_id": "2c3453b8-f07b-449c-9082-645aaf20110b",
          "response": [
            "Poor"
          ]
        },
        {
          "question_id": "7608d6a2-3f1e-4916-8932-12965909b3c1",
          "response": [
            "Good"
          ]
        },
        {
          "question_id": "9b990472-85f5-4622-b340-4944b160020e",
          "response": [
            "Friend/Family referral"
          ]
        },
        {
          "question_id": "aaf68f76-f975-48df-8760-dc333aef5ac6",
          "response": [
            "Definitely yes",
            "Might or might not"
          ]
        },
        {
          "question_id": "dc9b9442-3703-40f8-b715-a873fdd619f3",
          "response": [
            "Monthly"
          ]
        },
        {
          "question_id": "ed93db8c-29a0-453e-bef9-f5e0faf85a8e",
          "response": [
            "Very difficult"
          ]
        },
        {
          "question_id": "efce93d3-e2fb-4f5f-b05c-f26c19cfd126",
          "response": [
            "36-45"
          ]
        }
      ],
      "created_at": "2024-03-09 12:45:49",
      "__class__": "Response"
    },
    {
      "bio": {
        "name": "Okeomasilachi",
        "sex": "trans-Gender"
      },
      "timestamp": "2024-03-09 12:00:51",
      "id": "4e5cfdac-8908-4854-b5c0-7a382020f078",
      "updated_at": "2024-03-09 12:00:52",
      "survey_id": "3eada031-35a4-4569-9c98-0525d43de043",
      "answers": [
        {
          "question_id": "01f702fc-5ae6-4850-b7aa-d53b4b061f90",
          "response": [
            "Extremely likely"
          ]
        },
        {
          "question_id": "26eeecd9-1d5f-4736-8c02-8163ab47d4a4",
          "response": [
            "Satisfied"
          ]
        },
        {
          "question_id": "2c3453b8-f07b-449c-9082-645aaf20110b",
          "response": [
            "Very good"
          ]
        },
        {
          "question_id": "7608d6a2-3f1e-4916-8932-12965909b3c1",
          "response": [
            "Very good"
          ]
        },
        {
          "question_id": "9b990472-85f5-4622-b340-4944b160020e",
          "response": [
            "Social media"
          ]
        },
        {
          "question_id": "aaf68f76-f975-48df-8760-dc333aef5ac6",
          "response": [
            "Probably not"
          ]
        },
        {
          "question_id": "dc9b9442-3703-40f8-b715-a873fdd619f3",
          "response": [
            "First-time customer"
          ]
        },
        {
          "question_id": "ed93db8c-29a0-453e-bef9-f5e0faf85a8e",
          "response": [
            "Very difficult"
          ]
        },
        {
          "question_id": "efce93d3-e2fb-4f5f-b05c-f26c19cfd126",
          "response": [
            "26-35"
          ]
        }
      ],
      "created_at": "2024-03-09 12:00:52",
      "__class__": "Response"
    },
    {
      "bio": {
        "name": "Okeomasilachi",
        "sex": "male"
      },
      "timestamp": "2024-03-09 12:03:29",
      "id": "66eea092-4e94-4d3a-8a40-4d13e33bc3d5",
      "updated_at": "2024-03-09 12:04:48",
      "survey_id": "3eada031-35a4-4569-9c98-0525d43de043",
      "answers": [
        {
          "question_id": "01f702fc-5ae6-4850-b7aa-d53b4b061f90",
          "response": [
            "Likely",
            "Extremely unlikely"
          ]
        },
        {
          "question_id": "26eeecd9-1d5f-4736-8c02-8163ab47d4a4",
          "response": [
            "Extremely dissatisfied"
          ]
        },
        {
          "question_id": "2c3453b8-f07b-449c-9082-645aaf20110b",
          "response": [
            "Very good"
          ]
        },
        {
          "question_id": "7608d6a2-3f1e-4916-8932-12965909b3c1",
          "response": [
            "Poor"
          ]
        },
        {
          "question_id": "9b990472-85f5-4622-b340-4944b160020e",
          "response": [
            "Friend/Family referral"
          ]
        },
        {
          "question_id": "aaf68f76-f975-48df-8760-dc333aef5ac6",
          "response": [
            "Might or might not"
          ]
        },
        {
          "question_id": "dc9b9442-3703-40f8-b715-a873fdd619f3",
          "response": [
            "Daily"
          ]
        },
        {
          "question_id": "ed93db8c-29a0-453e-bef9-f5e0faf85a8e",
          "response": [
            "Very easy"
          ]
        },
        {
          "question_id": "efce93d3-e2fb-4f5f-b05c-f26c19cfd126",
          "response": [
            "18-25"
          ]
        }
      ],
      "created_at": "2024-03-09 12:04:48",
      "__class__": "Response"
    },
    {
      "bio": {
        "name": "Okeomasilachi",
        "sex": "trans-Gender"
      },
      "timestamp": "2024-03-09 12:03:29",
      "id": "743737bf-2d4f-4c06-9e1f-28990ce59e87",
      "updated_at": "2024-03-09 12:22:20",
      "survey_id": "3eada031-35a4-4569-9c98-0525d43de043",
      "answers": [
        {
          "question_id": "01f702fc-5ae6-4850-b7aa-d53b4b061f90",
          "response": [
            "Extremely likely"
          ]
        },
        {
          "question_id": "26eeecd9-1d5f-4736-8c02-8163ab47d4a4",
          "response": [
            "Extremely satisfied"
          ]
        },
        {
          "question_id": "2c3453b8-f07b-449c-9082-645aaf20110b",
          "response": [
            "Excellent"
          ]
        },
        {
          "question_id": "7608d6a2-3f1e-4916-8932-12965909b3c1",
          "response": [
            "Excellent"
          ]
        },
        {
          "question_id": "9b990472-85f5-4622-b340-4944b160020e",
          "response": [
            "Online search"
          ]
        },
        {
          "question_id": "aaf68f76-f975-48df-8760-dc333aef5ac6",
          "response": [
            "Definitely yes",
            "Definitely not"
          ]
        },
        {
          "question_id": "dc9b9442-3703-40f8-b715-a873fdd619f3",
          "response": [
            "First-time customer"
          ]
        },
        {
          "question_id": "ed93db8c-29a0-453e-bef9-f5e0faf85a8e",
          "response": [
            "Very easy"
          ]
        },
        {
          "question_id": "efce93d3-e2fb-4f5f-b05c-f26c19cfd126",
          "response": [
            "18-25"
          ]
        }
      ],
      "created_at": "2024-03-09 12:22:20",
      "__class__": "Response"
    },
    {
      "bio": {
        "name": "Okeomasilachi",
        "sex": "male"
      },
      "timestamp": "2024-03-09 12:03:29",
      "id": "79788138-06cb-496e-8b70-42628e8e5d87",
      "updated_at": "2024-03-09 12:21:22",
      "survey_id": "3eada031-35a4-4569-9c98-0525d43de043",
      "answers": [
        {
          "question_id": "01f702fc-5ae6-4850-b7aa-d53b4b061f90",
          "response": [
            "Extremely likely"
          ]
        },
        {
          "question_id": "26eeecd9-1d5f-4736-8c02-8163ab47d4a4",
          "response": [
            "Extremely satisfied"
          ]
        },
        {
          "question_id": "2c3453b8-f07b-449c-9082-645aaf20110b",
          "response": [
            "Excellent"
          ]
        },
        {
          "question_id": "7608d6a2-3f1e-4916-8932-12965909b3c1",
          "response": [
            "Good"
          ]
        },
        {
          "question_id": "9b990472-85f5-4622-b340-4944b160020e",
          "response": [
            "Online search"
          ]
        },
        {
          "question_id": "aaf68f76-f975-48df-8760-dc333aef5ac6",
          "response": [
            "Probably yes"
          ]
        },
        {
          "question_id": "dc9b9442-3703-40f8-b715-a873fdd619f3",
          "response": [
            "Occasionally"
          ]
        },
        {
          "question_id": "ed93db8c-29a0-453e-bef9-f5e0faf85a8e",
          "response": [
            "Very difficult"
          ]
        },
        {
          "question_id": "efce93d3-e2fb-4f5f-b05c-f26c19cfd126",
          "response": [
            "36-45"
          ]
        }
      ],
      "created_at": "2024-03-09 12:21:22",
      "__class__": "Response"
    },
    {
      "bio": {
        "name": "Okeomasilachi",
        "sex": "female"
      },
      "timestamp": "2024-03-09 12:38:57",
      "id": "7dd3f978-e952-4b20-8a20-63b606f86693",
      "updated_at": "2024-03-09 12:44:07",
      "survey_id": "3eada031-35a4-4569-9c98-0525d43de043",
      "answers": [
        {
          "question_id": "01f702fc-5ae6-4850-b7aa-d53b4b061f90",
          "response": [
            "Extremely likely"
          ]
        },
        {
          "question_id": "26eeecd9-1d5f-4736-8c02-8163ab47d4a4",
          "response": [
            "Extremely dissatisfied"
          ]
        },
        {
          "question_id": "2c3453b8-f07b-449c-9082-645aaf20110b",
          "response": [
            "Very good"
          ]
        },
        {
          "question_id": "7608d6a2-3f1e-4916-8932-12965909b3c1",
          "response": [
            "Poor"
          ]
        },
        {
          "question_id": "9b990472-85f5-4622-b340-4944b160020e",
          "response": [
            "Other (please specify)"
          ]
        },
        {
          "question_id": "aaf68f76-f975-48df-8760-dc333aef5ac6",
          "response": [
            "Probably not"
          ]
        },
        {
          "question_id": "dc9b9442-3703-40f8-b715-a873fdd619f3",
          "response": [
            "Occasionally"
          ]
        },
        {
          "question_id": "ed93db8c-29a0-453e-bef9-f5e0faf85a8e",
          "response": [
            "Very easy"
          ]
        },
        {
          "question_id": "efce93d3-e2fb-4f5f-b05c-f26c19cfd126",
          "response": [
            "18-25"
          ]
        }
      ],
      "created_at": "2024-03-09 12:44:07",
      "__class__": "Response"
    },
    {
      "bio": {
        "name": "Okeomasilachi",
        "sex": "trans-Gender"
      },
      "timestamp": "2024-03-09 11:08:15",
      "id": "81ee2846-a2e5-41b2-a0fa-077f442e566f",
      "updated_at": "2024-03-09 11:37:49",
      "survey_id": "3eada031-35a4-4569-9c98-0525d43de043",
      "answers": [
        {
          "question_id": "01f702fc-5ae6-4850-b7aa-d53b4b061f90",
          "response": [
            "Extremely likely"
          ]
        },
        {
          "question_id": "26eeecd9-1d5f-4736-8c02-8163ab47d4a4",
          "response": [
            "Satisfied"
          ]
        },
        {
          "question_id": "2c3453b8-f07b-449c-9082-645aaf20110b",
          "response": [
            "Very good"
          ]
        },
        {
          "question_id": "7608d6a2-3f1e-4916-8932-12965909b3c1",
          "response": [
            "Very good"
          ]
        },
        {
          "question_id": "9b990472-85f5-4622-b340-4944b160020e",
          "response": [
            "Social media"
          ]
        },
        {
          "question_id": "aaf68f76-f975-48df-8760-dc333aef5ac6",
          "response": [
            "Probably not"
          ]
        },
        {
          "question_id": "dc9b9442-3703-40f8-b715-a873fdd619f3",
          "response": [
            "First-time customer"
          ]
        },
        {
          "question_id": "ed93db8c-29a0-453e-bef9-f5e0faf85a8e",
          "response": [
            "Very difficult"
          ]
        },
        {
          "question_id": "efce93d3-e2fb-4f5f-b05c-f26c19cfd126",
          "response": [
            "26-35"
          ]
        }
      ],
      "created_at": "2024-03-09 11:37:49",
      "__class__": "Response"
    },
    {
      "bio": {
        "name": "Okeomasilachi",
        "sex": "trans-Gender"
      },
      "timestamp": "2024-03-09 11:58:40",
      "id": "84a6a6e6-b630-41ec-bfe0-de94df57927e",
      "updated_at": "2024-03-09 11:58:49",
      "survey_id": "3eada031-35a4-4569-9c98-0525d43de043",
      "answers": [
        {
          "question_id": "01f702fc-5ae6-4850-b7aa-d53b4b061f90",
          "response": [
            "Extremely likely"
          ]
        },
        {
          "question_id": "26eeecd9-1d5f-4736-8c02-8163ab47d4a4",
          "response": [
            "Satisfied"
          ]
        },
        {
          "question_id": "2c3453b8-f07b-449c-9082-645aaf20110b",
          "response": [
            "Very good"
          ]
        },
        {
          "question_id": "7608d6a2-3f1e-4916-8932-12965909b3c1",
          "response": [
            "Very good"
          ]
        },
        {
          "question_id": "9b990472-85f5-4622-b340-4944b160020e",
          "response": [
            "Social media"
          ]
        },
        {
          "question_id": "aaf68f76-f975-48df-8760-dc333aef5ac6",
          "response": [
            "Probably not"
          ]
        },
        {
          "question_id": "dc9b9442-3703-40f8-b715-a873fdd619f3",
          "response": [
            "First-time customer"
          ]
        },
        {
          "question_id": "ed93db8c-29a0-453e-bef9-f5e0faf85a8e",
          "response": [
            "Very difficult"
          ]
        },
        {
          "question_id": "efce93d3-e2fb-4f5f-b05c-f26c19cfd126",
          "response": [
            "26-35"
          ]
        }
      ],
      "created_at": "2024-03-09 11:58:49",
      "__class__": "Response"
    },
    {
      "bio": {
        "name": "Okeomasilachi",
        "sex": "female"
      },
      "timestamp": "2024-03-09 12:38:57",
      "id": "85896247-6496-4233-8421-f77fc03c5226",
      "updated_at": "2024-03-09 12:44:12",
      "survey_id": "3eada031-35a4-4569-9c98-0525d43de043",
      "answers": [
        {
          "question_id": "01f702fc-5ae6-4850-b7aa-d53b4b061f90",
          "response": [
            "Extremely likely"
          ]
        },
        {
          "question_id": "26eeecd9-1d5f-4736-8c02-8163ab47d4a4",
          "response": [
            "Extremely dissatisfied"
          ]
        },
        {
          "question_id": "2c3453b8-f07b-449c-9082-645aaf20110b",
          "response": [
            "Very good"
          ]
        },
        {
          "question_id": "7608d6a2-3f1e-4916-8932-12965909b3c1",
          "response": [
            "Poor"
          ]
        },
        {
          "question_id": "9b990472-85f5-4622-b340-4944b160020e",
          "response": [
            "Other (please specify)"
          ]
        },
        {
          "question_id": "aaf68f76-f975-48df-8760-dc333aef5ac6",
          "response": [
            "Probably not"
          ]
        },
        {
          "question_id": "dc9b9442-3703-40f8-b715-a873fdd619f3",
          "response": [
            "Occasionally"
          ]
        },
        {
          "question_id": "ed93db8c-29a0-453e-bef9-f5e0faf85a8e",
          "response": [
            "Very easy"
          ]
        },
        {
          "question_id": "efce93d3-e2fb-4f5f-b05c-f26c19cfd126",
          "response": [
            "18-25"
          ]
        }
      ],
      "created_at": "2024-03-09 12:44:12",
      "__class__": "Response"
    },
    {
      "bio": {
        "name": "Okeomasilachi",
        "sex": "male"
      },
      "timestamp": "2024-03-09 12:03:29",
      "id": "97623e27-16c9-492b-89b6-2cde7801af6c",
      "updated_at": "2024-03-09 12:19:14",
      "survey_id": "3eada031-35a4-4569-9c98-0525d43de043",
      "answers": [
        {
          "question_id": "01f702fc-5ae6-4850-b7aa-d53b4b061f90",
          "response": [
            "Extremely likely"
          ]
        },
        {
          "question_id": "26eeecd9-1d5f-4736-8c02-8163ab47d4a4",
          "response": [
            "Extremely satisfied"
          ]
        },
        {
          "question_id": "2c3453b8-f07b-449c-9082-645aaf20110b",
          "response": [
            "Excellent"
          ]
        },
        {
          "question_id": "7608d6a2-3f1e-4916-8932-12965909b3c1",
          "response": [
            "Good"
          ]
        },
        {
          "question_id": "9b990472-85f5-4622-b340-4944b160020e",
          "response": [
            "Online search"
          ]
        },
        {
          "question_id": "aaf68f76-f975-48df-8760-dc333aef5ac6",
          "response": [
            "Probably yes"
          ]
        },
        {
          "question_id": "dc9b9442-3703-40f8-b715-a873fdd619f3",
          "response": [
            "Occasionally"
          ]
        },
        {
          "question_id": "ed93db8c-29a0-453e-bef9-f5e0faf85a8e",
          "response": [
            "Very difficult"
          ]
        },
        {
          "question_id": "efce93d3-e2fb-4f5f-b05c-f26c19cfd126",
          "response": [
            "36-45"
          ]
        }
      ],
      "created_at": "2024-03-09 12:19:14",
      "__class__": "Response"
    },
    {
      "bio": {
        "name": "Okeomasilachi",
        "sex": "trans-Gender"
      },
      "timestamp": "2024-03-09 12:02:27",
      "id": "9e0d578e-845f-47ea-b157-edad1d5ad50c",
      "updated_at": "2024-03-09 12:02:31",
      "survey_id": "3eada031-35a4-4569-9c98-0525d43de043",
      "answers": [
        {
          "question_id": "01f702fc-5ae6-4850-b7aa-d53b4b061f90",
          "response": [
            "Extremely likely"
          ]
        },
        {
          "question_id": "26eeecd9-1d5f-4736-8c02-8163ab47d4a4",
          "response": [
            "Satisfied"
          ]
        },
        {
          "question_id": "2c3453b8-f07b-449c-9082-645aaf20110b",
          "response": [
            "Very good"
          ]
        },
        {
          "question_id": "7608d6a2-3f1e-4916-8932-12965909b3c1",
          "response": [
            "Very good"
          ]
        },
        {
          "question_id": "9b990472-85f5-4622-b340-4944b160020e",
          "response": [
            "Social media"
          ]
        },
        {
          "question_id": "aaf68f76-f975-48df-8760-dc333aef5ac6",
          "response": [
            "Probably not"
          ]
        },
        {
          "question_id": "dc9b9442-3703-40f8-b715-a873fdd619f3",
          "response": [
            "First-time customer"
          ]
        },
        {
          "question_id": "ed93db8c-29a0-453e-bef9-f5e0faf85a8e",
          "response": [
            "Very difficult"
          ]
        },
        {
          "question_id": "efce93d3-e2fb-4f5f-b05c-f26c19cfd126",
          "response": [
            "26-35"
          ]
        }
      ],
      "created_at": "2024-03-09 12:02:31",
      "__class__": "Response"
    },
    {
      "bio": {
        "name": "Okeomasilachi",
        "sex": "female"
      },
      "timestamp": "2024-03-09 12:38:57",
      "id": "ad6d8453-95a4-4bba-996d-02a41fbf8725",
      "updated_at": "2024-03-09 12:43:56",
      "survey_id": "3eada031-35a4-4569-9c98-0525d43de043",
      "answers": [
        {
          "question_id": "01f702fc-5ae6-4850-b7aa-d53b4b061f90",
          "response": [
            "Extremely likely"
          ]
        },
        {
          "question_id": "26eeecd9-1d5f-4736-8c02-8163ab47d4a4",
          "response": [
            "Extremely dissatisfied"
          ]
        },
        {
          "question_id": "2c3453b8-f07b-449c-9082-645aaf20110b",
          "response": [
            "Very good"
          ]
        },
        {
          "question_id": "7608d6a2-3f1e-4916-8932-12965909b3c1",
          "response": [
            "Poor"
          ]
        },
        {
          "question_id": "9b990472-85f5-4622-b340-4944b160020e",
          "response": [
            "Other (please specify)"
          ]
        },
        {
          "question_id": "aaf68f76-f975-48df-8760-dc333aef5ac6",
          "response": [
            "Probably not"
          ]
        },
        {
          "question_id": "dc9b9442-3703-40f8-b715-a873fdd619f3",
          "response": [
            "Occasionally"
          ]
        },
        {
          "question_id": "ed93db8c-29a0-453e-bef9-f5e0faf85a8e",
          "response": [
            "Very easy"
          ]
        },
        {
          "question_id": "efce93d3-e2fb-4f5f-b05c-f26c19cfd126",
          "response": [
            "18-25"
          ]
        }
      ],
      "created_at": "2024-03-09 12:43:56",
      "__class__": "Response"
    },
    {
      "bio": {
        "name": "Okeomasilachi",
        "sex": "female"
      },
      "timestamp": "2024-03-09 12:38:57",
      "id": "c51cb8c5-409b-430a-b351-1d99e0f40ac5",
      "updated_at": "2024-03-09 12:40:00",
      "survey_id": "3eada031-35a4-4569-9c98-0525d43de043",
      "answers": [
        {
          "question_id": "01f702fc-5ae6-4850-b7aa-d53b4b061f90",
          "response": [
            "Extremely likely"
          ]
        },
        {
          "question_id": "26eeecd9-1d5f-4736-8c02-8163ab47d4a4",
          "response": [
            "Extremely satisfied"
          ]
        },
        {
          "question_id": "2c3453b8-f07b-449c-9082-645aaf20110b",
          "response": [
            "Very good"
          ]
        },
        {
          "question_id": "7608d6a2-3f1e-4916-8932-12965909b3c1",
          "response": [
            "Very good"
          ]
        },
        {
          "question_id": "9b990472-85f5-4622-b340-4944b160020e",
          "response": [
            "Online search"
          ]
        },
        {
          "question_id": "aaf68f76-f975-48df-8760-dc333aef5ac6",
          "response": [
            "Definitely yes"
          ]
        },
        {
          "question_id": "dc9b9442-3703-40f8-b715-a873fdd619f3",
          "response": [
            "Weekly"
          ]
        },
        {
          "question_id": "ed93db8c-29a0-453e-bef9-f5e0faf85a8e",
          "response": [
            "Very easy"
          ]
        },
        {
          "question_id": "efce93d3-e2fb-4f5f-b05c-f26c19cfd126",
          "response": [
            "26-35"
          ]
        }
      ],
      "created_at": "2024-03-09 12:40:00",
      "__class__": "Response"
    },
    {
      "bio": {
        "name": "Okeomasilachi",
        "sex": "trans-Gender"
      },
      "timestamp": "2024-03-09 12:00:03",
      "id": "c52b68cf-f436-420a-a277-69ab7ebc90d3",
      "updated_at": "2024-03-09 12:00:08",
      "survey_id": "3eada031-35a4-4569-9c98-0525d43de043",
      "answers": [
        {
          "question_id": "01f702fc-5ae6-4850-b7aa-d53b4b061f90",
          "response": [
            "Extremely likely"
          ]
        },
        {
          "question_id": "26eeecd9-1d5f-4736-8c02-8163ab47d4a4",
          "response": [
            "Satisfied"
          ]
        },
        {
          "question_id": "2c3453b8-f07b-449c-9082-645aaf20110b",
          "response": [
            "Very good"
          ]
        },
        {
          "question_id": "7608d6a2-3f1e-4916-8932-12965909b3c1",
          "response": [
            "Very good"
          ]
        },
        {
          "question_id": "9b990472-85f5-4622-b340-4944b160020e",
          "response": [
            "Social media"
          ]
        },
        {
          "question_id": "aaf68f76-f975-48df-8760-dc333aef5ac6",
          "response": [
            "Probably not"
          ]
        },
        {
          "question_id": "dc9b9442-3703-40f8-b715-a873fdd619f3",
          "response": [
            "First-time customer"
          ]
        },
        {
          "question_id": "ed93db8c-29a0-453e-bef9-f5e0faf85a8e",
          "response": [
            "Very difficult"
          ]
        },
        {
          "question_id": "efce93d3-e2fb-4f5f-b05c-f26c19cfd126",
          "response": [
            "26-35"
          ]
        }
      ],
      "created_at": "2024-03-09 12:00:08",
      "__class__": "Response"
    },
    {
      "bio": {
        "name": "Okeomasilachi",
        "sex": "female"
      },
      "timestamp": "2024-03-09 12:03:29",
      "id": "ddbc2c29-6e7d-4c7c-9432-7bc7931ab1eb",
      "updated_at": "2024-03-09 12:24:35",
      "survey_id": "3eada031-35a4-4569-9c98-0525d43de043",
      "answers": [
        {
          "question_id": "01f702fc-5ae6-4850-b7aa-d53b4b061f90",
          "response": [
            "Extremely likely"
          ]
        },
        {
          "question_id": "26eeecd9-1d5f-4736-8c02-8163ab47d4a4",
          "response": [
            "Satisfied"
          ]
        },
        {
          "question_id": "2c3453b8-f07b-449c-9082-645aaf20110b",
          "response": [
            "Very good"
          ]
        },
        {
          "question_id": "7608d6a2-3f1e-4916-8932-12965909b3c1",
          "response": [
            "Very good"
          ]
        },
        {
          "question_id": "9b990472-85f5-4622-b340-4944b160020e",
          "response": [
            "Other (please specify)"
          ]
        },
        {
          "question_id": "aaf68f76-f975-48df-8760-dc333aef5ac6",
          "response": [
            "Definitely yes",
            "Definitely not"
          ]
        },
        {
          "question_id": "dc9b9442-3703-40f8-b715-a873fdd619f3",
          "response": []
        },
        {
          "question_id": "ed93db8c-29a0-453e-bef9-f5e0faf85a8e",
          "response": [
            "Easy"
          ]
        },
        {
          "question_id": "efce93d3-e2fb-4f5f-b05c-f26c19cfd126",
          "response": [
            "26-35"
          ]
        }
      ],
      "created_at": "2024-03-09 12:24:35",
      "__class__": "Response"
    },
    {
      "bio": {
        "name": "Okeomasilachi",
        "sex": "female"
      },
      "timestamp": "2024-03-09 12:38:57",
      "id": "e0cfcb51-6fe8-4766-80d9-3a1e888b5247",
      "updated_at": "2024-03-09 12:44:12",
      "survey_id": "3eada031-35a4-4569-9c98-0525d43de043",
      "answers": [
        {
          "question_id": "01f702fc-5ae6-4850-b7aa-d53b4b061f90",
          "response": [
            "Extremely likely"
          ]
        },
        {
          "question_id": "26eeecd9-1d5f-4736-8c02-8163ab47d4a4",
          "response": [
            "Extremely dissatisfied"
          ]
        },
        {
          "question_id": "2c3453b8-f07b-449c-9082-645aaf20110b",
          "response": [
            "Very good"
          ]
        },
        {
          "question_id": "7608d6a2-3f1e-4916-8932-12965909b3c1",
          "response": [
            "Poor"
          ]
        },
        {
          "question_id": "9b990472-85f5-4622-b340-4944b160020e",
          "response": [
            "Other (please specify)"
          ]
        },
        {
          "question_id": "aaf68f76-f975-48df-8760-dc333aef5ac6",
          "response": [
            "Probably not"
          ]
        },
        {
          "question_id": "dc9b9442-3703-40f8-b715-a873fdd619f3",
          "response": [
            "Occasionally"
          ]
        },
        {
          "question_id": "ed93db8c-29a0-453e-bef9-f5e0faf85a8e",
          "response": [
            "Very easy"
          ]
        },
        {
          "question_id": "efce93d3-e2fb-4f5f-b05c-f26c19cfd126",
          "response": [
            "18-25"
          ]
        }
      ],
      "created_at": "2024-03-09 12:44:12",
      "__class__": "Response"
    },
    {
      "bio": {
        "name": "Okeomasilachi",
        "sex": "trans-Gender"
      },
      "timestamp": "2024-03-09 12:02:09",
      "id": "f91b86f7-baab-4205-87c7-296d544874a2",
      "updated_at": "2024-03-09 12:02:11",
      "survey_id": "3eada031-35a4-4569-9c98-0525d43de043",
      "answers": [
        {
          "question_id": "01f702fc-5ae6-4850-b7aa-d53b4b061f90",
          "response": [
            "Extremely likely"
          ]
        },
        {
          "question_id": "26eeecd9-1d5f-4736-8c02-8163ab47d4a4",
          "response": [
            "Satisfied"
          ]
        },
        {
          "question_id": "2c3453b8-f07b-449c-9082-645aaf20110b",
          "response": [
            "Very good"
          ]
        },
        {
          "question_id": "7608d6a2-3f1e-4916-8932-12965909b3c1",
          "response": [
            "Very good"
          ]
        },
        {
          "question_id": "9b990472-85f5-4622-b340-4944b160020e",
          "response": [
            "Social media"
          ]
        },
        {
          "question_id": "aaf68f76-f975-48df-8760-dc333aef5ac6",
          "response": [
            "Probably not"
          ]
        },
        {
          "question_id": "dc9b9442-3703-40f8-b715-a873fdd619f3",
          "response": [
            "First-time customer"
          ]
        },
        {
          "question_id": "ed93db8c-29a0-453e-bef9-f5e0faf85a8e",
          "response": [
            "Very difficult"
          ]
        },
        {
          "question_id": "efce93d3-e2fb-4f5f-b05c-f26c19cfd126",
          "response": [
            "26-35"
          ]
        }
      ],
      "created_at": "2024-03-09 12:02:11",
      "__class__": "Response"
    }
  ]
}